python_teacher.py
python_teacher-1.1.5.dist-info/LICENSE
python_teacher-1.1.5.dist-info/METADATA
python_teacher-1.1.5.dist-info/WHEEL
python_teacher-1.1.5.dist-info/entry_points.txt
python_teacher-1.1.5.dist-info/RECORD
