Metadata-Version: 2.1
Name: python-teacher
Version: 1.1.5
Summary: A command line program to teach you python.
License: LICENSE
Author: Master Coder 1323
Author-email: sparlevi18@gmail.com
Requires-Python: >=3.11,<4.0
Classifier: License :: Other/Proprietary License
Classifier: Programming Language :: Python :: 3
Classifier: Programming Language :: Python :: 3.11
Classifier: Programming Language :: Python :: 3.12
